{".class":"MypyFile","_fullname":"src.scans.dns","future_import_flags":[],"is_partial_stub_package":false,"is_stub":false,"names":{".class":"SymbolTable","Any":{".class":"SymbolTableNode","cross_ref":"typing.Any","kind":"Gdef"},"DNS":{".class":"SymbolTableNode","kind":"Gdef","node":{".class":"Var","flags":["is_suppressed_import","is_ready","is_inferred"],"fullname":"src.scans.dns.DNS","name":"DNS","setter_type":null,"type":{".class":"AnyType","missing_import_name":"src.scans.dns.DNS","source_any":null,"type_of_any":3}}},"DNSQR":{".class":"SymbolTableNode","kind":"Gdef","node":{".class":"Var","flags":["is_suppressed_import","is_ready","is_inferred"],"fullname":"src.scans.dns.DNSQR","name":"DNSQR","setter_type":null,"type":{".class":"AnyType","missing_import_name":"src.scans.dns.DNSQR","source_any":null,"type_of_any":3}}},"IP":{".class":"SymbolTableNode","kind":"Gdef","node":{".class":"Var","flags":["is_suppressed_import","is_ready","is_inferred"],"fullname":"src.scans.dns.IP","name":"IP","setter_type":null,"type":{".class":"AnyType","missing_import_name":"src.scans.dns.IP","source_any":null,"type_of_any":3}}},"List":{".class":"SymbolTableNode","cross_ref":"typing.List","kind":"Gdef"},"UDP":{".class":"SymbolTableNode","kind":"Gdef","node":{".class":"Var","flags":["is_suppressed_import","is_ready","is_inferred"],"fullname":"src.scans.dns.UDP","name":"UDP","setter_type":null,"type":{".class":"AnyType","missing_import_name":"src.scans.dns.UDP","source_any":null,"type_of_any":3}}},"_PRIVATE_NETS":{".class":"SymbolTableNode","kind":"Gdef","node":{".class":"Var","flags":["is_inferred","has_explicit_value"],"fullname":"src.scans.dns._PRIVATE_NETS","name":"_PRIVATE_NETS","setter_type":null,"type":{".class":"Instance","args":[{".class":"UnionType","items":["ipaddress.IPv4Network","ipaddress.IPv6Network"],"uses_pep604_syntax":false}],"extra_attrs":null,"type_ref":"builtins.list"}}},"__annotations__":{".class":"SymbolTableNode","kind":"Gdef","node":{".class":"Var","flags":["is_ready"],"fullname":"src.scans.dns.__annotations__","name":"__annotations__","setter_type":null,"type":{".class":"Instance","args":["builtins.str",{".class":"AnyType","missing_import_name":null,"source_any":null,"type_of_any":6}],"extra_attrs":null,"type_ref":"builtins.dict"}}},"__doc__":{".class":"SymbolTableNode","kind":"Gdef","node":{".class":"Var","flags":["is_ready"],"fullname":"src.scans.dns.__doc__","name":"__doc__","setter_type":null,"type":"builtins.str"}},"__file__":{".class":"SymbolTableNode","kind":"Gdef","node":{".class":"Var","flags":["is_ready"],"fullname":"src.scans.dns.__file__","name":"__file__","setter_type":null,"type":"builtins.str"}},"__name__":{".class":"SymbolTableNode","kind":"Gdef","node":{".class":"Var","flags":["is_ready"],"fullname":"src.scans.dns.__name__","name":"__name__","setter_type":null,"type":"builtins.str"}},"__package__":{".class":"SymbolTableNode","kind":"Gdef","node":{".class":"Var","flags":["is_ready"],"fullname":"src.scans.dns.__package__","name":"__package__","setter_type":null,"type":"builtins.str"}},"__spec__":{".class":"SymbolTableNode","kind":"Gdef","node":{".class":"Var","flags":["is_ready"],"fullname":"src.scans.dns.__spec__","name":"__spec__","setter_type":null,"type":"_frozen_importlib.ModuleSpec"}},"_get_nameservers":{".class":"SymbolTableNode","kind":"Gdef","node":{".class":"FuncDef","abstract_status":0,"arg_kinds":[1],"arg_names":["path"],"dataclass_transform_spec":null,"deprecated":null,"flags":[],"fullname":"src.scans.dns._get_nameservers","name":"_get_nameservers","type":{".class":"CallableType","arg_kinds":[1],"arg_names":["path"],"arg_types":["builtins.str"],"def_extras":{"first_arg":null},"fallback":"builtins.function","from_concatenate":false,"implicit":false,"imprecise_arg_kinds":false,"is_bound":false,"is_ellipsis_args":false,"name":"_get_nameservers","ret_type":{".class":"Instance","args":["builtins.str"],"extra_attrs":null,"type_ref":"builtins.list"},"type_guard":null,"type_is":null,"unpack_kwargs":false,"variables":[]}}},"_is_private":{".class":"SymbolTableNode","kind":"Gdef","node":{".class":"FuncDef","abstract_status":0,"arg_kinds":[0],"arg_names":["ip"],"dataclass_transform_spec":null,"deprecated":null,"flags":[],"fullname":"src.scans.dns._is_private","name":"_is_private","type":{".class":"CallableType","arg_kinds":[0],"arg_names":["ip"],"arg_types":["builtins.str"],"def_extras":{"first_arg":null},"fallback":"builtins.function","from_concatenate":false,"implicit":false,"imprecise_arg_kinds":false,"is_bound":false,"is_ellipsis_args":false,"name":"_is_private","ret_type":"builtins.bool","type_guard":null,"type_is":null,"unpack_kwargs":false,"variables":[]}}},"ip_address":{".class":"SymbolTableNode","cross_ref":"ipaddress.ip_address","kind":"Gdef"},"ip_network":{".class":"SymbolTableNode","cross_ref":"ipaddress.ip_network","kind":"Gdef"},"scan":{".class":"SymbolTableNode","kind":"Gdef","node":{".class":"FuncDef","abstract_status":0,"arg_kinds":[],"arg_names":[],"dataclass_transform_spec":null,"deprecated":null,"flags":[],"fullname":"src.scans.dns.scan","name":"scan","type":{".class":"CallableType","arg_kinds":[],"arg_names":[],"arg_types":[],"def_extras":{"first_arg":null},"fallback":"builtins.function","from_concatenate":false,"implicit":false,"imprecise_arg_kinds":false,"is_bound":false,"is_ellipsis_args":false,"name":"scan","ret_type":{".class":"Instance","args":[{".class":"AnyType","missing_import_name":null,"source_any":null,"type_of_any":4},{".class":"AnyType","missing_import_name":null,"source_any":null,"type_of_any":4}],"extra_attrs":null,"type_ref":"builtins.dict"},"type_guard":null,"type_is":null,"unpack_kwargs":false,"variables":[]}}},"sr1":{".class":"SymbolTableNode","cross_ref":"scapy.sendrecv.sr1","kind":"Gdef"}},"path":"src\\scans\\dns.py"}