{".class":"MypyFile","_fullname":"geoip2.records","future_import_flags":[],"is_partial_stub_package":false,"is_stub":false,"names":{".class":"SymbolTable","ABCMeta":{".class":"SymbolTableNode","cross_ref":"abc.ABCMeta","kind":"Gdef"},"City":{".class":"SymbolTableNode","kind":"Gdef","node":{".class":"TypeInfo","_promote":[],"abstract_attributes":[],"alt_promote":null,"bases":["geoip2.records.PlaceRecord"],"dataclass_transform_spec":null,"declared_metaclass":null,"defn":{".class":"ClassDef","fullname":"geoip2.records.City","name":"City","type_vars":[]},"deletable_attributes":[],"deprecated":null,"flags":[],"fullname":"geoip2.records.City","has_param_spec_type":false,"metaclass_type":"abc.ABCMeta","metadata":{},"module_name":"geoip2.records","mro":["geoip2.records.City","geoip2.records.PlaceRecord","geoip2.records.Record","geoip2._internal.Model","builtins.object"],"names":{".class":"SymbolTable","__init__":{".class":"SymbolTableNode","kind":"Mdef","node":{".class":"FuncDef","abstract_status":0,"arg_kinds":[0,0,5,5,5,4],"arg_names":["self","locales","confidence","geoname_id","names","_"],"dataclass_transform_spec":null,"deprecated":null,"flags":["is_trivial_self"],"fullname":"geoip2.records.City.__init__","name":"__init__","type":{".class":"CallableType","arg_kinds":[0,0,5,5,5,4],"arg_names":["self","locales","confidence","geoname_id","names","_"],"arg_types":["geoip2.records.City",{".class":"UnionType","items":[{".class":"Instance","args":["builtins.str"],"extra_attrs":null,"type_ref":"typing.Sequence"},{".class":"NoneType"}],"uses_pep604_syntax":false},{".class":"UnionType","items":["builtins.int",{".class":"NoneType"}],"uses_pep604_syntax":false},{".class":"UnionType","items":["builtins.int",{".class":"NoneType"}],"uses_pep604_syntax":false},{".class":"UnionType","items":[{".class":"Instance","args":["builtins.str","builtins.str"],"extra_attrs":null,"type_ref":"builtins.dict"},{".class":"NoneType"}],"uses_pep604_syntax":false},{".class":"AnyType","missing_import_name":null,"source_any":null,"type_of_any":1}],"def_extras":{"first_arg":"self"},"fallback":"builtins.function","from_concatenate":false,"implicit":false,"imprecise_arg_kinds":false,"is_bound":false,"is_ellipsis_args":false,"name":"__init__ of City","ret_type":{".class":"NoneType"},"type_guard":null,"type_is":null,"unpack_kwargs":false,"variables":[]}}},"confidence":{".class":"SymbolTableNode","kind":"Mdef","node":{".class":"Var","flags":["is_initialized_in_class","is_ready"],"fullname":"geoip2.records.City.confidence","name":"confidence","setter_type":null,"type":{".class":"UnionType","items":["builtins.int",{".class":"NoneType"}],"uses_pep604_syntax":false}}},"geoname_id":{".class":"SymbolTableNode","kind":"Mdef","node":{".class":"Var","flags":["is_initialized_in_class","is_ready"],"fullname":"geoip2.records.City.geoname_id","name":"geoname_id","setter_type":null,"type":{".class":"UnionType","items":["builtins.int",{".class":"NoneType"}],"uses_pep604_syntax":false}}}},"self_type":{".class":"TypeVarType","default":{".class":"AnyType","missing_import_name":null,"source_any":null,"type_of_any":4},"fullname":"geoip2.records.City.Self","id":0,"name":"Self","namespace":"","upper_bound":"geoip2.records.City","values":[],"variance":0},"slots":null,"tuple_type":null,"type_vars":[],"typeddict_type":null}},"Continent":{".class":"SymbolTableNode","kind":"Gdef","node":{".class":"TypeInfo","_promote":[],"abstract_attributes":[],"alt_promote":null,"bases":["geoip2.records.PlaceRecord"],"dataclass_transform_spec":null,"declared_metaclass":null,"defn":{".class":"ClassDef","fullname":"geoip2.records.Continent","name":"Continent","type_vars":[]},"deletable_attributes":[],"deprecated":null,"flags":[],"fullname":"geoip2.records.Continent","has_param_spec_type":false,"metaclass_type":"abc.ABCMeta","metadata":{},"module_name":"geoip2.records","mro":["geoip2.records.Continent","geoip2.records.PlaceRecord","geoip2.records.Record","geoip2._internal.Model","builtins.object"],"names":{".class":"SymbolTable","__init__":{".class":"SymbolTableNode","kind":"Mdef","node":{".class":"FuncDef","abstract_status":0,"arg_kinds":[0,0,5,5,5,4],"arg_names":["self","locales","code","geoname_id","names","_"],"dataclass_transform_spec":null,"deprecated":null,"flags":["is_trivial_self"],"fullname":"geoip2.records.Continent.__init__","name":"__init__","type":{".class":"CallableType","arg_kinds":[0,0,5,5,5,4],"arg_names":["self","locales","code","geoname_id","names","_"],"arg_types":["geoip2.records.Continent",{".class":"UnionType","items":[{".class":"Instance","args":["builtins.str"],"extra_attrs":null,"type_ref":"typing.Sequence"},{".class":"NoneType"}],"uses_pep604_syntax":false},{".class":"UnionType","items":["builtins.str",{".class":"NoneType"}],"uses_pep604_syntax":false},{".class":"UnionType","items":["builtins.int",{".class":"NoneType"}],"uses_pep604_syntax":false},{".class":"UnionType","items":[{".class":"Instance","args":["builtins.str","builtins.str"],"extra_attrs":null,"type_ref":"builtins.dict"},{".class":"NoneType"}],"uses_pep604_syntax":false},{".class":"AnyType","missing_import_name":null,"source_any":null,"type_of_any":1}],"def_extras":{"first_arg":"self"},"fallback":"builtins.function","from_concatenate":false,"implicit":false,"imprecise_arg_kinds":false,"is_bound":false,"is_ellipsis_args":false,"name":"__init__ of Continent","ret_type":{".class":"NoneType"},"type_guard":null,"type_is":null,"unpack_kwargs":false,"variables":[]}}},"code":{".class":"SymbolTableNode","kind":"Mdef","node":{".class":"Var","flags":["is_initialized_in_class","is_ready"],"fullname":"geoip2.records.Continent.code","name":"code","setter_type":null,"type":{".class":"UnionType","items":["builtins.str",{".class":"NoneType"}],"uses_pep604_syntax":false}}},"geoname_id":{".class":"SymbolTableNode","kind":"Mdef","node":{".class":"Var","flags":["is_initialized_in_class","is_ready"],"fullname":"geoip2.records.Continent.geoname_id","name":"geoname_id","setter_type":null,"type":{".class":"UnionType","items":["builtins.int",{".class":"NoneType"}],"uses_pep604_syntax":false}}}},"self_type":{".class":"TypeVarType","default":{".class":"AnyType","missing_import_name":null,"source_any":null,"type_of_any":4},"fullname":"geoip2.records.Continent.Self","id":0,"name":"Self","namespace":"","upper_bound":"geoip2.records.Continent","values":[],"variance":0},"slots":null,"tuple_type":null,"type_vars":[],"typeddict_type":null}},"Country":{".class":"SymbolTableNode","kind":"Gdef","node":{".class":"TypeInfo","_promote":[],"abstract_attributes":[],"alt_promote":null,"bases":["geoip2.records.PlaceRecord"],"dataclass_transform_spec":null,"declared_metaclass":null,"defn":{".class":"ClassDef","fullname":"geoip2.records.Country","name":"Country","type_vars":[]},"deletable_attributes":[],"deprecated":null,"flags":[],"fullname":"geoip2.records.Country","has_param_spec_type":false,"metaclass_type":"abc.ABCMeta","metadata":{},"module_name":"geoip2.records","mro":["geoip2.records.Country","geoip2.records.PlaceRecord","geoip2.records.Record","geoip2._internal.Model","builtins.object"],"names":{".class":"SymbolTable","__init__":{".class":"SymbolTableNode","kind":"Mdef","node":{".class":"FuncDef","abstract_status":0,"arg_kinds":[0,0,5,5,5,5,5,4],"arg_names":["self","locales","confidence","geoname_id","is_in_european_union","iso_code","names","_"],"dataclass_transform_spec":null,"deprecated":null,"flags":["is_trivial_self"],"fullname":"geoip2.records.Country.__init__","name":"__init__","type":{".class":"CallableType","arg_kinds":[0,0,5,5,5,5,5,4],"arg_names":["self","locales","confidence","geoname_id","is_in_european_union","iso_code","names","_"],"arg_types":["geoip2.records.Country",{".class":"UnionType","items":[{".class":"Instance","args":["builtins.str"],"extra_attrs":null,"type_ref":"typing.Sequence"},{".class":"NoneType"}],"uses_pep604_syntax":false},{".class":"UnionType","items":["builtins.int",{".class":"NoneType"}],"uses_pep604_syntax":false},{".class":"UnionType","items":["builtins.int",{".class":"NoneType"}],"uses_pep604_syntax":false},"builtins.bool",{".class":"UnionType","items":["builtins.str",{".class":"NoneType"}],"uses_pep604_syntax":false},{".class":"UnionType","items":[{".class":"Instance","args":["builtins.str","builtins.str"],"extra_attrs":null,"type_ref":"builtins.dict"},{".class":"NoneType"}],"uses_pep604_syntax":false},{".class":"AnyType","missing_import_name":null,"source_any":null,"type_of_any":1}],"def_extras":{"first_arg":"self"},"fallback":"builtins.function","from_concatenate":false,"implicit":false,"imprecise_arg_kinds":false,"is_bound":false,"is_ellipsis_args":false,"name":"__init__ of Country","ret_type":{".class":"NoneType"},"type_guard":null,"type_is":null,"unpack_kwargs":false,"variables":[]}}},"confidence":{".class":"SymbolTableNode","kind":"Mdef","node":{".class":"Var","flags":["is_initialized_in_class","is_ready"],"fullname":"geoip2.records.Country.confidence","name":"confidence","setter_type":null,"type":{".class":"UnionType","items":["builtins.int",{".class":"NoneType"}],"uses_pep604_syntax":false}}},"geoname_id":{".class":"SymbolTableNode","kind":"Mdef","node":{".class":"Var","flags":["is_initialized_in_class","is_ready"],"fullname":"geoip2.records.Country.geoname_id","name":"geoname_id","setter_type":null,"type":{".class":"UnionType","items":["builtins.int",{".class":"NoneType"}],"uses_pep604_syntax":false}}},"is_in_european_union":{".class":"SymbolTableNode","kind":"Mdef","node":{".class":"Var","flags":["is_initialized_in_class","is_ready"],"fullname":"geoip2.records.Country.is_in_european_union","name":"is_in_european_union","setter_type":null,"type":"builtins.bool"}},"iso_code":{".class":"SymbolTableNode","kind":"Mdef","node":{".class":"Var","flags":["is_initialized_in_class","is_ready"],"fullname":"geoip2.records.Country.iso_code","name":"iso_code","setter_type":null,"type":{".class":"UnionType","items":["builtins.str",{".class":"NoneType"}],"uses_pep604_syntax":false}}}},"self_type":{".class":"TypeVarType","default":{".class":"AnyType","missing_import_name":null,"source_any":null,"type_of_any":4},"fullname":"geoip2.records.Country.Self","id":0,"name":"Self","namespace":"","upper_bound":"geoip2.records.Country","values":[],"variance":0},"slots":null,"tuple_type":null,"type_vars":[],"typeddict_type":null}},"IPAddress":{".class":"SymbolTableNode","cross_ref":"geoip2.types.IPAddress","kind":"Gdef"},"IPv4Address":{".class":"SymbolTableNode","cross_ref":"ipaddress.IPv4Address","kind":"Gdef"},"IPv6Address":{".class":"SymbolTableNode","cross_ref":"ipaddress.IPv6Address","kind":"Gdef"},"Location":{".class":"SymbolTableNode","kind":"Gdef","node":{".class":"TypeInfo","_promote":[],"abstract_attributes":[],"alt_promote":null,"bases":["geoip2.records.Record"],"dataclass_transform_spec":null,"declared_metaclass":null,"defn":{".class":"ClassDef","fullname":"geoip2.records.Location","name":"Location","type_vars":[]},"deletable_attributes":[],"deprecated":null,"flags":[],"fullname":"geoip2.records.Location","has_param_spec_type":false,"metaclass_type":"abc.ABCMeta","metadata":{},"module_name":"geoip2.records","mro":["geoip2.records.Location","geoip2.records.Record","geoip2._internal.Model","builtins.object"],"names":{".class":"SymbolTable","__init__":{".class":"SymbolTableNode","kind":"Mdef","node":{".class":"FuncDef","abstract_status":0,"arg_kinds":[0,5,5,5,5,5,5,5,4],"arg_names":["self","average_income","accuracy_radius","latitude","longitude","metro_code","population_density","time_zone","_"],"dataclass_transform_spec":null,"deprecated":null,"flags":["is_trivial_self"],"fullname":"geoip2.records.Location.__init__","name":"__init__","type":{".class":"CallableType","arg_kinds":[0,5,5,5,5,5,5,5,4],"arg_names":["self","average_income","accuracy_radius","latitude","longitude","metro_code","population_density","time_zone","_"],"arg_types":["geoip2.records.Location",{".class":"UnionType","items":["builtins.int",{".class":"NoneType"}],"uses_pep604_syntax":false},{".class":"UnionType","items":["builtins.int",{".class":"NoneType"}],"uses_pep604_syntax":false},{".class":"UnionType","items":["builtins.float",{".class":"NoneType"}],"uses_pep604_syntax":false},{".class":"UnionType","items":["builtins.float",{".class":"NoneType"}],"uses_pep604_syntax":false},{".class":"UnionType","items":["builtins.int",{".class":"NoneType"}],"uses_pep604_syntax":false},{".class":"UnionType","items":["builtins.int",{".class":"NoneType"}],"uses_pep604_syntax":false},{".class":"UnionType","items":["builtins.str",{".class":"NoneType"}],"uses_pep604_syntax":false},{".class":"AnyType","missing_import_name":null,"source_any":null,"type_of_any":1}],"def_extras":{"first_arg":"self"},"fallback":"builtins.function","from_concatenate":false,"implicit":false,"imprecise_arg_kinds":false,"is_bound":false,"is_ellipsis_args":false,"name":"__init__ of Location","ret_type":{".class":"NoneType"},"type_guard":null,"type_is":null,"unpack_kwargs":false,"variables":[]}}},"accuracy_radius":{".class":"SymbolTableNode","kind":"Mdef","node":{".class":"Var","flags":["is_initialized_in_class","is_ready"],"fullname":"geoip2.records.Location.accuracy_radius","name":"accuracy_radius","setter_type":null,"type":{".class":"UnionType","items":["builtins.int",{".class":"NoneType"}],"uses_pep604_syntax":false}}},"average_income":{".class":"SymbolTableNode","kind":"Mdef","node":{".class":"Var","flags":["is_initialized_in_class","is_ready"],"fullname":"geoip2.records.Location.average_income","name":"average_income","setter_type":null,"type":{".class":"UnionType","items":["builtins.int",{".class":"NoneType"}],"uses_pep604_syntax":false}}},"latitude":{".class":"SymbolTableNode","kind":"Mdef","node":{".class":"Var","flags":["is_initialized_in_class","is_ready"],"fullname":"geoip2.records.Location.latitude","name":"latitude","setter_type":null,"type":{".class":"UnionType","items":["builtins.float",{".class":"NoneType"}],"uses_pep604_syntax":false}}},"longitude":{".class":"SymbolTableNode","kind":"Mdef","node":{".class":"Var","flags":["is_initialized_in_class","is_ready"],"fullname":"geoip2.records.Location.longitude","name":"longitude","setter_type":null,"type":{".class":"UnionType","items":["builtins.float",{".class":"NoneType"}],"uses_pep604_syntax":false}}},"metro_code":{".class":"SymbolTableNode","kind":"Mdef","node":{".class":"Var","flags":["is_initialized_in_class","is_ready"],"fullname":"geoip2.records.Location.metro_code","name":"metro_code","setter_type":null,"type":{".class":"UnionType","items":["builtins.int",{".class":"NoneType"}],"uses_pep604_syntax":false}}},"population_density":{".class":"SymbolTableNode","kind":"Mdef","node":{".class":"Var","flags":["is_initialized_in_class","is_ready"],"fullname":"geoip2.records.Location.population_density","name":"population_density","setter_type":null,"type":{".class":"UnionType","items":["builtins.int",{".class":"NoneType"}],"uses_pep604_syntax":false}}},"time_zone":{".class":"SymbolTableNode","kind":"Mdef","node":{".class":"Var","flags":["is_initialized_in_class","is_ready"],"fullname":"geoip2.records.Location.time_zone","name":"time_zone","setter_type":null,"type":{".class":"UnionType","items":["builtins.str",{".class":"NoneType"}],"uses_pep604_syntax":false}}}},"self_type":{".class":"TypeVarType","default":{".class":"AnyType","missing_import_name":null,"source_any":null,"type_of_any":4},"fullname":"geoip2.records.Location.Self","id":0,"name":"Self","namespace":"","upper_bound":"geoip2.records.Location","values":[],"variance":0},"slots":null,"tuple_type":null,"type_vars":[],"typeddict_type":null}},"MaxMind":{".class":"SymbolTableNode","kind":"Gdef","node":{".class":"TypeInfo","_promote":[],"abstract_attributes":[],"alt_promote":null,"bases":["geoip2.records.Record"],"dataclass_transform_spec":null,"declared_metaclass":null,"defn":{".class":"ClassDef","fullname":"geoip2.records.MaxMind","name":"MaxMind","type_vars":[]},"deletable_attributes":[],"deprecated":null,"flags":[],"fullname":"geoip2.records.MaxMind","has_param_spec_type":false,"metaclass_type":"abc.ABCMeta","metadata":{},"module_name":"geoip2.records","mro":["geoip2.records.MaxMind","geoip2.records.Record","geoip2._internal.Model","builtins.object"],"names":{".class":"SymbolTable","__init__":{".class":"SymbolTableNode","kind":"Mdef","node":{".class":"FuncDef","abstract_status":0,"arg_kinds":[0,5,4],"arg_names":["self","queries_remaining","_"],"dataclass_transform_spec":null,"deprecated":null,"flags":["is_trivial_self"],"fullname":"geoip2.records.MaxMind.__init__","name":"__init__","type":{".class":"CallableType","arg_kinds":[0,5,4],"arg_names":["self","queries_remaining","_"],"arg_types":["geoip2.records.MaxMind",{".class":"UnionType","items":["builtins.int",{".class":"NoneType"}],"uses_pep604_syntax":false},{".class":"AnyType","missing_import_name":null,"source_any":null,"type_of_any":1}],"def_extras":{"first_arg":"self"},"fallback":"builtins.function","from_concatenate":false,"implicit":false,"imprecise_arg_kinds":false,"is_bound":false,"is_ellipsis_args":false,"name":"__init__ of MaxMind","ret_type":{".class":"NoneType"},"type_guard":null,"type_is":null,"unpack_kwargs":false,"variables":[]}}},"queries_remaining":{".class":"SymbolTableNode","kind":"Mdef","node":{".class":"Var","flags":["is_initialized_in_class","is_ready"],"fullname":"geoip2.records.MaxMind.queries_remaining","name":"queries_remaining","setter_type":null,"type":{".class":"UnionType","items":["builtins.int",{".class":"NoneType"}],"uses_pep604_syntax":false}}}},"self_type":{".class":"TypeVarType","default":{".class":"AnyType","missing_import_name":null,"source_any":null,"type_of_any":4},"fullname":"geoip2.records.MaxMind.Self","id":0,"name":"Self","namespace":"","upper_bound":"geoip2.records.MaxMind","values":[],"variance":0},"slots":null,"tuple_type":null,"type_vars":[],"typeddict_type":null}},"Model":{".class":"SymbolTableNode","cross_ref":"geoip2._internal.Model","kind":"Gdef"},"Optional":{".class":"SymbolTableNode","cross_ref":"typing.Optional","kind":"Gdef"},"PlaceRecord":{".class":"SymbolTableNode","kind":"Gdef","node":{".class":"TypeInfo","_promote":[],"abstract_attributes":[],"alt_promote":null,"bases":["geoip2.records.Record"],"dataclass_transform_spec":null,"declared_metaclass":"abc.ABCMeta","defn":{".class":"ClassDef","fullname":"geoip2.records.PlaceRecord","name":"PlaceRecord","type_vars":[]},"deletable_attributes":[],"deprecated":null,"flags":[],"fullname":"geoip2.records.PlaceRecord","has_param_spec_type":false,"metaclass_type":"abc.ABCMeta","metadata":{},"module_name":"geoip2.records","mro":["geoip2.records.PlaceRecord","geoip2.records.Record","geoip2._internal.Model","builtins.object"],"names":{".class":"SymbolTable","__init__":{".class":"SymbolTableNode","kind":"Mdef","node":{".class":"FuncDef","abstract_status":0,"arg_kinds":[0,0,0],"arg_names":["self","locales","names"],"dataclass_transform_spec":null,"deprecated":null,"flags":["is_trivial_self"],"fullname":"geoip2.records.PlaceRecord.__init__","name":"__init__","type":{".class":"CallableType","arg_kinds":[0,0,0],"arg_names":["self","locales","names"],"arg_types":["geoip2.records.PlaceRecord",{".class":"UnionType","items":[{".class":"Instance","args":["builtins.str"],"extra_attrs":null,"type_ref":"typing.Sequence"},{".class":"NoneType"}],"uses_pep604_syntax":false},{".class":"UnionType","items":[{".class":"Instance","args":["builtins.str","builtins.str"],"extra_attrs":null,"type_ref":"builtins.dict"},{".class":"NoneType"}],"uses_pep604_syntax":false}],"def_extras":{"first_arg":"self"},"fallback":"builtins.function","from_concatenate":false,"implicit":false,"imprecise_arg_kinds":false,"is_bound":false,"is_ellipsis_args":false,"name":"__init__ of PlaceRecord","ret_type":{".class":"NoneType"},"type_guard":null,"type_is":null,"unpack_kwargs":false,"variables":[]}}},"_locales":{".class":"SymbolTableNode","kind":"Mdef","node":{".class":"Var","flags":["is_initialized_in_class","is_ready"],"fullname":"geoip2.records.PlaceRecord._locales","name":"_locales","setter_type":null,"type":{".class":"Instance","args":["builtins.str"],"extra_attrs":null,"type_ref":"typing.Sequence"}}},"name":{".class":"SymbolTableNode","kind":"Mdef","node":{".class":"Decorator","func":{".class":"FuncDef","abstract_status":0,"arg_kinds":[0],"arg_names":["self"],"dataclass_transform_spec":null,"deprecated":null,"flags":["is_property","is_decorated","is_trivial_self"],"fullname":"geoip2.records.PlaceRecord.name","name":"name","type":{".class":"CallableType","arg_kinds":[0],"arg_names":["self"],"arg_types":["geoip2.records.PlaceRecord"],"def_extras":{"first_arg":"self"},"fallback":"builtins.function","from_concatenate":false,"implicit":false,"imprecise_arg_kinds":false,"is_bound":false,"is_ellipsis_args":false,"name":"name of PlaceRecord","ret_type":{".class":"UnionType","items":["builtins.str",{".class":"NoneType"}],"uses_pep604_syntax":false},"type_guard":null,"type_is":null,"unpack_kwargs":false,"variables":[]}},"is_overload":false,"var":{".class":"Var","flags":["is_initialized_in_class","is_property","is_ready","is_inferred"],"fullname":"geoip2.records.PlaceRecord.name","name":"name","setter_type":null,"type":{".class":"CallableType","arg_kinds":[0],"arg_names":["self"],"arg_types":["geoip2.records.PlaceRecord"],"def_extras":{"first_arg":"self"},"fallback":"builtins.function","from_concatenate":false,"implicit":false,"imprecise_arg_kinds":false,"is_bound":false,"is_ellipsis_args":false,"name":"name of PlaceRecord","ret_type":{".class":"UnionType","items":["builtins.str",{".class":"NoneType"}],"uses_pep604_syntax":false},"type_guard":null,"type_is":null,"unpack_kwargs":false,"variables":[]}}}},"names":{".class":"SymbolTableNode","kind":"Mdef","node":{".class":"Var","flags":["is_initialized_in_class","is_ready"],"fullname":"geoip2.records.PlaceRecord.names","name":"names","setter_type":null,"type":{".class":"Instance","args":["builtins.str","builtins.str"],"extra_attrs":null,"type_ref":"builtins.dict"}}}},"self_type":{".class":"TypeVarType","default":{".class":"AnyType","missing_import_name":null,"source_any":null,"type_of_any":4},"fullname":"geoip2.records.PlaceRecord.Self","id":0,"name":"Self","namespace":"","upper_bound":"geoip2.records.PlaceRecord","values":[],"variance":0},"slots":null,"tuple_type":null,"type_vars":[],"typeddict_type":null}},"Postal":{".class":"SymbolTableNode","kind":"Gdef","node":{".class":"TypeInfo","_promote":[],"abstract_attributes":[],"alt_promote":null,"bases":["geoip2.records.Record"],"dataclass_transform_spec":null,"declared_metaclass":null,"defn":{".class":"ClassDef","fullname":"geoip2.records.Postal","name":"Postal","type_vars":[]},"deletable_attributes":[],"deprecated":null,"flags":[],"fullname":"geoip2.records.Postal","has_param_spec_type":false,"metaclass_type":"abc.ABCMeta","metadata":{},"module_name":"geoip2.records","mro":["geoip2.records.Postal","geoip2.records.Record","geoip2._internal.Model","builtins.object"],"names":{".class":"SymbolTable","__init__":{".class":"SymbolTableNode","kind":"Mdef","node":{".class":"FuncDef","abstract_status":0,"arg_kinds":[0,5,5,4],"arg_names":["self","code","confidence","_"],"dataclass_transform_spec":null,"deprecated":null,"flags":["is_trivial_self"],"fullname":"geoip2.records.Postal.__init__","name":"__init__","type":{".class":"CallableType","arg_kinds":[0,5,5,4],"arg_names":["self","code","confidence","_"],"arg_types":["geoip2.records.Postal",{".class":"UnionType","items":["builtins.str",{".class":"NoneType"}],"uses_pep604_syntax":false},{".class":"UnionType","items":["builtins.int",{".class":"NoneType"}],"uses_pep604_syntax":false},{".class":"AnyType","missing_import_name":null,"source_any":null,"type_of_any":1}],"def_extras":{"first_arg":"self"},"fallback":"builtins.function","from_concatenate":false,"implicit":false,"imprecise_arg_kinds":false,"is_bound":false,"is_ellipsis_args":false,"name":"__init__ of Postal","ret_type":{".class":"NoneType"},"type_guard":null,"type_is":null,"unpack_kwargs":false,"variables":[]}}},"code":{".class":"SymbolTableNode","kind":"Mdef","node":{".class":"Var","flags":["is_initialized_in_class","is_ready"],"fullname":"geoip2.records.Postal.code","name":"code","setter_type":null,"type":{".class":"UnionType","items":["builtins.str",{".class":"NoneType"}],"uses_pep604_syntax":false}}},"confidence":{".class":"SymbolTableNode","kind":"Mdef","node":{".class":"Var","flags":["is_initialized_in_class","is_ready"],"fullname":"geoip2.records.Postal.confidence","name":"confidence","setter_type":null,"type":{".class":"UnionType","items":["builtins.int",{".class":"NoneType"}],"uses_pep604_syntax":false}}}},"self_type":{".class":"TypeVarType","default":{".class":"AnyType","missing_import_name":null,"source_any":null,"type_of_any":4},"fullname":"geoip2.records.Postal.Self","id":0,"name":"Self","namespace":"","upper_bound":"geoip2.records.Postal","values":[],"variance":0},"slots":null,"tuple_type":null,"type_vars":[],"typeddict_type":null}},"Record":{".class":"SymbolTableNode","kind":"Gdef","node":{".class":"TypeInfo","_promote":[],"abstract_attributes":[],"alt_promote":null,"bases":["geoip2._internal.Model"],"dataclass_transform_spec":null,"declared_metaclass":"abc.ABCMeta","defn":{".class":"ClassDef","fullname":"geoip2.records.Record","name":"Record","type_vars":[]},"deletable_attributes":[],"deprecated":null,"flags":[],"fullname":"geoip2.records.Record","has_param_spec_type":false,"metaclass_type":"abc.ABCMeta","metadata":{},"module_name":"geoip2.records","mro":["geoip2.records.Record","geoip2._internal.Model","builtins.object"],"names":{".class":"SymbolTable","__repr__":{".class":"SymbolTableNode","kind":"Mdef","node":{".class":"FuncDef","abstract_status":0,"arg_kinds":[0],"arg_names":[null],"dataclass_transform_spec":null,"deprecated":null,"flags":["is_trivial_self"],"fullname":"geoip2.records.Record.__repr__","name":"__repr__","type":{".class":"CallableType","arg_kinds":[0],"arg_names":[null],"arg_types":["geoip2.records.Record"],"def_extras":{"first_arg":"self"},"fallback":"builtins.function","from_concatenate":false,"implicit":false,"imprecise_arg_kinds":false,"is_bound":false,"is_ellipsis_args":false,"name":"__repr__ of Record","ret_type":"builtins.str","type_guard":null,"type_is":null,"unpack_kwargs":false,"variables":[]}}}},"self_type":{".class":"TypeVarType","default":{".class":"AnyType","missing_import_name":null,"source_any":null,"type_of_any":4},"fullname":"geoip2.records.Record.Self","id":0,"name":"Self","namespace":"","upper_bound":"geoip2.records.Record","values":[],"variance":0},"slots":null,"tuple_type":null,"type_vars":[],"typeddict_type":null}},"RepresentedCountry":{".class":"SymbolTableNode","kind":"Gdef","node":{".class":"TypeInfo","_promote":[],"abstract_attributes":[],"alt_promote":null,"bases":["geoip2.records.Country"],"dataclass_transform_spec":null,"declared_metaclass":null,"defn":{".class":"ClassDef","fullname":"geoip2.records.RepresentedCountry","name":"RepresentedCountry","type_vars":[]},"deletable_attributes":[],"deprecated":null,"flags":[],"fullname":"geoip2.records.RepresentedCountry","has_param_spec_type":false,"metaclass_type":"abc.ABCMeta","metadata":{},"module_name":"geoip2.records","mro":["geoip2.records.RepresentedCountry","geoip2.records.Country","geoip2.records.PlaceRecord","geoip2.records.Record","geoip2._internal.Model","builtins.object"],"names":{".class":"SymbolTable","__init__":{".class":"SymbolTableNode","kind":"Mdef","node":{".class":"FuncDef","abstract_status":0,"arg_kinds":[0,0,5,5,5,5,5,5,4],"arg_names":["self","locales","confidence","geoname_id","is_in_european_union","iso_code","names","type","_"],"dataclass_transform_spec":null,"deprecated":null,"flags":["is_trivial_self"],"fullname":"geoip2.records.RepresentedCountry.__init__","name":"__init__","type":{".class":"CallableType","arg_kinds":[0,0,5,5,5,5,5,5,4],"arg_names":["self","locales","confidence","geoname_id","is_in_european_union","iso_code","names","type","_"],"arg_types":["geoip2.records.RepresentedCountry",{".class":"UnionType","items":[{".class":"Instance","args":["builtins.str"],"extra_attrs":null,"type_ref":"typing.Sequence"},{".class":"NoneType"}],"uses_pep604_syntax":false},{".class":"UnionType","items":["builtins.int",{".class":"NoneType"}],"uses_pep604_syntax":false},{".class":"UnionType","items":["builtins.int",{".class":"NoneType"}],"uses_pep604_syntax":false},"builtins.bool",{".class":"UnionType","items":["builtins.str",{".class":"NoneType"}],"uses_pep604_syntax":false},{".class":"UnionType","items":[{".class":"Instance","args":["builtins.str","builtins.str"],"extra_attrs":null,"type_ref":"builtins.dict"},{".class":"NoneType"}],"uses_pep604_syntax":false},{".class":"UnionType","items":["builtins.str",{".class":"NoneType"}],"uses_pep604_syntax":false},{".class":"AnyType","missing_import_name":null,"source_any":null,"type_of_any":1}],"def_extras":{"first_arg":"self"},"fallback":"builtins.function","from_concatenate":false,"implicit":false,"imprecise_arg_kinds":false,"is_bound":false,"is_ellipsis_args":false,"name":"__init__ of RepresentedCountry","ret_type":{".class":"NoneType"},"type_guard":null,"type_is":null,"unpack_kwargs":false,"variables":[]}}},"type":{".class":"SymbolTableNode","kind":"Mdef","node":{".class":"Var","flags":["is_initialized_in_class","is_ready"],"fullname":"geoip2.records.RepresentedCountry.type","name":"type","setter_type":null,"type":{".class":"UnionType","items":["builtins.str",{".class":"NoneType"}],"uses_pep604_syntax":false}}}},"self_type":{".class":"TypeVarType","default":{".class":"AnyType","missing_import_name":null,"source_any":null,"type_of_any":4},"fullname":"geoip2.records.RepresentedCountry.Self","id":0,"name":"Self","namespace":"","upper_bound":"geoip2.records.RepresentedCountry","values":[],"variance":0},"slots":null,"tuple_type":null,"type_vars":[],"typeddict_type":null}},"Sequence":{".class":"SymbolTableNode","cross_ref":"typing.Sequence","kind":"Gdef"},"Subdivision":{".class":"SymbolTableNode","kind":"Gdef","node":{".class":"TypeInfo","_promote":[],"abstract_attributes":[],"alt_promote":null,"bases":["geoip2.records.PlaceRecord"],"dataclass_transform_spec":null,"declared_metaclass":null,"defn":{".class":"ClassDef","fullname":"geoip2.records.Subdivision","name":"Subdivision","type_vars":[]},"deletable_attributes":[],"deprecated":null,"flags":[],"fullname":"geoip2.records.Subdivision","has_param_spec_type":false,"metaclass_type":"abc.ABCMeta","metadata":{},"module_name":"geoip2.records","mro":["geoip2.records.Subdivision","geoip2.records.PlaceRecord","geoip2.records.Record","geoip2._internal.Model","builtins.object"],"names":{".class":"SymbolTable","__init__":{".class":"SymbolTableNode","kind":"Mdef","node":{".class":"FuncDef","abstract_status":0,"arg_kinds":[0,0,5,5,5,5,4],"arg_names":["self","locales","confidence","geoname_id","iso_code","names","_"],"dataclass_transform_spec":null,"deprecated":null,"flags":["is_trivial_self"],"fullname":"geoip2.records.Subdivision.__init__","name":"__init__","type":{".class":"CallableType","arg_kinds":[0,0,5,5,5,5,4],"arg_names":["self","locales","confidence","geoname_id","iso_code","names","_"],"arg_types":["geoip2.records.Subdivision",{".class":"UnionType","items":[{".class":"Instance","args":["builtins.str"],"extra_attrs":null,"type_ref":"typing.Sequence"},{".class":"NoneType"}],"uses_pep604_syntax":false},{".class":"UnionType","items":["builtins.int",{".class":"NoneType"}],"uses_pep604_syntax":false},{".class":"UnionType","items":["builtins.int",{".class":"NoneType"}],"uses_pep604_syntax":false},{".class":"UnionType","items":["builtins.str",{".class":"NoneType"}],"uses_pep604_syntax":false},{".class":"UnionType","items":[{".class":"Instance","args":["builtins.str","builtins.str"],"extra_attrs":null,"type_ref":"builtins.dict"},{".class":"NoneType"}],"uses_pep604_syntax":false},{".class":"AnyType","missing_import_name":null,"source_any":null,"type_of_any":1}],"def_extras":{"first_arg":"self"},"fallback":"builtins.function","from_concatenate":false,"implicit":false,"imprecise_arg_kinds":false,"is_bound":false,"is_ellipsis_args":false,"name":"__init__ of Subdivision","ret_type":{".class":"NoneType"},"type_guard":null,"type_is":null,"unpack_kwargs":false,"variables":[]}}},"confidence":{".class":"SymbolTableNode","kind":"Mdef","node":{".class":"Var","flags":["is_initialized_in_class","is_ready"],"fullname":"geoip2.records.Subdivision.confidence","name":"confidence","setter_type":null,"type":{".class":"UnionType","items":["builtins.int",{".class":"NoneType"}],"uses_pep604_syntax":false}}},"geoname_id":{".class":"SymbolTableNode","kind":"Mdef","node":{".class":"Var","flags":["is_initialized_in_class","is_ready"],"fullname":"geoip2.records.Subdivision.geoname_id","name":"geoname_id","setter_type":null,"type":{".class":"UnionType","items":["builtins.int",{".class":"NoneType"}],"uses_pep604_syntax":false}}},"iso_code":{".class":"SymbolTableNode","kind":"Mdef","node":{".class":"Var","flags":["is_initialized_in_class","is_ready"],"fullname":"geoip2.records.Subdivision.iso_code","name":"iso_code","setter_type":null,"type":{".class":"UnionType","items":["builtins.str",{".class":"NoneType"}],"uses_pep604_syntax":false}}}},"self_type":{".class":"TypeVarType","default":{".class":"AnyType","missing_import_name":null,"source_any":null,"type_of_any":4},"fullname":"geoip2.records.Subdivision.Self","id":0,"name":"Self","namespace":"","upper_bound":"geoip2.records.Subdivision","values":[],"variance":0},"slots":null,"tuple_type":null,"type_vars":[],"typeddict_type":null}},"Subdivisions":{".class":"SymbolTableNode","kind":"Gdef","node":{".class":"TypeInfo","_promote":[],"abstract_attributes":[],"alt_promote":null,"bases":[{".class":"Instance","args":[{".class":"AnyType","missing_import_name":null,"source_any":null,"type_of_any":4}],"extra_attrs":null,"type_ref":"builtins.tuple"}],"dataclass_transform_spec":null,"declared_metaclass":null,"defn":{".class":"ClassDef","fullname":"geoip2.records.Subdivisions","name":"Subdivisions","type_vars":[]},"deletable_attributes":[],"deprecated":null,"flags":[],"fullname":"geoip2.records.Subdivisions","has_param_spec_type":false,"metaclass_type":"abc.ABCMeta","metadata":{},"module_name":"geoip2.records","mro":["geoip2.records.Subdivisions","builtins.tuple","typing.Sequence","typing.Reversible","typing.Collection","typing.Iterable","typing.Container","builtins.object"],"names":{".class":"SymbolTable","__init__":{".class":"SymbolTableNode","kind":"Mdef","node":{".class":"FuncDef","abstract_status":0,"arg_kinds":[0,0,2],"arg_names":["self","locales","subdivisions"],"dataclass_transform_spec":null,"deprecated":null,"flags":["is_trivial_self"],"fullname":"geoip2.records.Subdivisions.__init__","name":"__init__","type":{".class":"CallableType","arg_kinds":[0,0,2],"arg_names":["self","locales","subdivisions"],"arg_types":["geoip2.records.Subdivisions",{".class":"UnionType","items":[{".class":"Instance","args":["builtins.str"],"extra_attrs":null,"type_ref":"typing.Sequence"},{".class":"NoneType"}],"uses_pep604_syntax":false},{".class":"AnyType","missing_import_name":null,"source_any":null,"type_of_any":1}],"def_extras":{"first_arg":"self"},"fallback":"builtins.function","from_concatenate":false,"implicit":false,"imprecise_arg_kinds":false,"is_bound":false,"is_ellipsis_args":false,"name":"__init__ of Subdivisions","ret_type":{".class":"NoneType"},"type_guard":null,"type_is":null,"unpack_kwargs":false,"variables":[]}}},"__new__":{".class":"SymbolTableNode","kind":"Mdef","node":{".class":"FuncDef","abstract_status":0,"arg_kinds":[0,0,2],"arg_names":["cls","locales","subdivisions"],"dataclass_transform_spec":null,"deprecated":null,"flags":["is_static"],"fullname":"geoip2.records.Subdivisions.__new__","name":"__new__","type":{".class":"CallableType","arg_kinds":[0,0,2],"arg_names":["cls","locales","subdivisions"],"arg_types":[{".class":"TypeType","item":"geoip2.records.Subdivisions"},{".class":"UnionType","items":[{".class":"Instance","args":["builtins.str"],"extra_attrs":null,"type_ref":"typing.Sequence"},{".class":"NoneType"}],"uses_pep604_syntax":false},{".class":"AnyType","missing_import_name":null,"source_any":null,"type_of_any":1}],"def_extras":{"first_arg":null},"fallback":"builtins.function","from_concatenate":false,"implicit":false,"imprecise_arg_kinds":false,"is_bound":false,"is_ellipsis_args":false,"name":"__new__ of Subdivisions","ret_type":"geoip2.records.Subdivisions","type_guard":null,"type_is":null,"unpack_kwargs":false,"variables":[]}}},"_locales":{".class":"SymbolTableNode","implicit":true,"kind":"Mdef","node":{".class":"Var","flags":["is_inferred"],"fullname":"geoip2.records.Subdivisions._locales","name":"_locales","setter_type":null,"type":{".class":"UnionType","items":[{".class":"Instance","args":["builtins.str"],"extra_attrs":null,"type_ref":"typing.Sequence"},{".class":"NoneType"}],"uses_pep604_syntax":false}}},"most_specific":{".class":"SymbolTableNode","kind":"Mdef","node":{".class":"Decorator","func":{".class":"FuncDef","abstract_status":0,"arg_kinds":[0],"arg_names":["self"],"dataclass_transform_spec":null,"deprecated":null,"flags":["is_property","is_decorated","is_trivial_self"],"fullname":"geoip2.records.Subdivisions.most_specific","name":"most_specific","type":{".class":"CallableType","arg_kinds":[0],"arg_names":["self"],"arg_types":["geoip2.records.Subdivisions"],"def_extras":{"first_arg":"self"},"fallback":"builtins.function","from_concatenate":false,"implicit":false,"imprecise_arg_kinds":false,"is_bound":false,"is_ellipsis_args":false,"name":"most_specific of Subdivisions","ret_type":"geoip2.records.Subdivision","type_guard":null,"type_is":null,"unpack_kwargs":false,"variables":[]}},"is_overload":false,"var":{".class":"Var","flags":["is_initialized_in_class","is_property","is_ready","is_inferred"],"fullname":"geoip2.records.Subdivisions.most_specific","name":"most_specific","setter_type":null,"type":{".class":"CallableType","arg_kinds":[0],"arg_names":["self"],"arg_types":["geoip2.records.Subdivisions"],"def_extras":{"first_arg":"self"},"fallback":"builtins.function","from_concatenate":false,"implicit":false,"imprecise_arg_kinds":false,"is_bound":false,"is_ellipsis_args":false,"name":"most_specific of Subdivisions","ret_type":"geoip2.records.Subdivision","type_guard":null,"type_is":null,"unpack_kwargs":false,"variables":[]}}}}},"self_type":{".class":"TypeVarType","default":{".class":"AnyType","missing_import_name":null,"source_any":null,"type_of_any":4},"fullname":"geoip2.records.Subdivisions.Self","id":0,"name":"Self","namespace":"","upper_bound":"geoip2.records.Subdivisions","values":[],"variance":0},"slots":null,"tuple_type":null,"type_vars":[],"typeddict_type":null}},"Traits":{".class":"SymbolTableNode","kind":"Gdef","node":{".class":"TypeInfo","_promote":[],"abstract_attributes":[],"alt_promote":null,"bases":["geoip2.records.Record"],"dataclass_transform_spec":null,"declared_metaclass":null,"defn":{".class":"ClassDef","fullname":"geoip2.records.Traits","name":"Traits","type_vars":[]},"deletable_attributes":[],"deprecated":null,"flags":[],"fullname":"geoip2.records.Traits","has_param_spec_type":false,"metaclass_type":"abc.ABCMeta","metadata":{},"module_name":"geoip2.records","mro":["geoip2.records.Traits","geoip2.records.Record","geoip2._internal.Model","builtins.object"],"names":{".class":"SymbolTable","__init__":{".class":"SymbolTableNode","kind":"Mdef","node":{".class":"FuncDef","abstract_status":0,"arg_kinds":[0,5,5,5,5,5,5,5,5,5,5,5,5,5,5,5,5,5,5,5,5,5,5,5,5,4],"arg_names":["self","autonomous_system_number","autonomous_system_organization","connection_type","domain","is_anonymous","is_anonymous_proxy","is_anonymous_vpn","is_hosting_provider","is_legitimate_proxy","is_public_proxy","is_residential_proxy","is_satellite_provider","is_tor_exit_node","isp","ip_address","network","organization","prefix_len","static_ip_score","user_count","user_type","mobile_country_code","mobile_network_code","is_anycast","_"],"dataclass_transform_spec":null,"deprecated":null,"flags":["is_trivial_self"],"fullname":"geoip2.records.Traits.__init__","name":"__init__","type":{".class":"CallableType","arg_kinds":[0,5,5,5,5,5,5,5,5,5,5,5,5,5,5,5,5,5,5,5,5,5,5,5,5,4],"arg_names":["self","autonomous_system_number","autonomous_system_organization","connection_type","domain","is_anonymous","is_anonymous_proxy","is_anonymous_vpn","is_hosting_provider","is_legitimate_proxy","is_public_proxy","is_residential_proxy","is_satellite_provider","is_tor_exit_node","isp","ip_address","network","organization","prefix_len","static_ip_score","user_count","user_type","mobile_country_code","mobile_network_code","is_anycast","_"],"arg_types":["geoip2.records.Traits",{".class":"UnionType","items":["builtins.int",{".class":"NoneType"}],"uses_pep604_syntax":false},{".class":"UnionType","items":["builtins.str",{".class":"NoneType"}],"uses_pep604_syntax":false},{".class":"UnionType","items":["builtins.str",{".class":"NoneType"}],"uses_pep604_syntax":false},{".class":"UnionType","items":["builtins.str",{".class":"NoneType"}],"uses_pep604_syntax":false},"builtins.bool","builtins.bool","builtins.bool","builtins.bool","builtins.bool","builtins.bool","builtins.bool","builtins.bool","builtins.bool",{".class":"UnionType","items":["builtins.str",{".class":"NoneType"}],"uses_pep604_syntax":false},{".class":"UnionType","items":["builtins.str",{".class":"NoneType"}],"uses_pep604_syntax":false},{".class":"UnionType","items":["builtins.str",{".class":"NoneType"}],"uses_pep604_syntax":false},{".class":"UnionType","items":["builtins.str",{".class":"NoneType"}],"uses_pep604_syntax":false},{".class":"UnionType","items":["builtins.int",{".class":"NoneType"}],"uses_pep604_syntax":false},{".class":"UnionType","items":["builtins.float",{".class":"NoneType"}],"uses_pep604_syntax":false},{".class":"UnionType","items":["builtins.int",{".class":"NoneType"}],"uses_pep604_syntax":false},{".class":"UnionType","items":["builtins.str",{".class":"NoneType"}],"uses_pep604_syntax":false},{".class":"UnionType","items":["builtins.str",{".class":"NoneType"}],"uses_pep604_syntax":false},{".class":"UnionType","items":["builtins.str",{".class":"NoneType"}],"uses_pep604_syntax":false},"builtins.bool",{".class":"AnyType","missing_import_name":null,"source_any":null,"type_of_any":1}],"def_extras":{"first_arg":"self"},"fallback":"builtins.function","from_concatenate":false,"implicit":false,"imprecise_arg_kinds":false,"is_bound":false,"is_ellipsis_args":false,"name":"__init__ of Traits","ret_type":{".class":"NoneType"},"type_guard":null,"type_is":null,"unpack_kwargs":false,"variables":[]}}},"_ip_address":{".class":"SymbolTableNode","kind":"Mdef","node":{".class":"Var","flags":["is_initialized_in_class","is_ready"],"fullname":"geoip2.records.Traits._ip_address","name":"_ip_address","setter_type":null,"type":{".class":"UnionType","items":[{".class":"TypeAliasType","args":[],"type_ref":"geoip2.types.IPAddress"},{".class":"NoneType"}],"uses_pep604_syntax":false}}},"_network":{".class":"SymbolTableNode","kind":"Mdef","node":{".class":"Var","flags":["is_initialized_in_class","is_ready"],"fullname":"geoip2.records.Traits._network","name":"_network","setter_type":null,"type":{".class":"UnionType","items":["ipaddress.IPv4Network","ipaddress.IPv6Network",{".class":"NoneType"}],"uses_pep604_syntax":false}}},"_prefix_len":{".class":"SymbolTableNode","kind":"Mdef","node":{".class":"Var","flags":["is_initialized_in_class","is_ready"],"fullname":"geoip2.records.Traits._prefix_len","name":"_prefix_len","setter_type":null,"type":{".class":"UnionType","items":["builtins.int",{".class":"NoneType"}],"uses_pep604_syntax":false}}},"autonomous_system_number":{".class":"SymbolTableNode","kind":"Mdef","node":{".class":"Var","flags":["is_initialized_in_class","is_ready"],"fullname":"geoip2.records.Traits.autonomous_system_number","name":"autonomous_system_number","setter_type":null,"type":{".class":"UnionType","items":["builtins.int",{".class":"NoneType"}],"uses_pep604_syntax":false}}},"autonomous_system_organization":{".class":"SymbolTableNode","kind":"Mdef","node":{".class":"Var","flags":["is_initialized_in_class","is_ready"],"fullname":"geoip2.records.Traits.autonomous_system_organization","name":"autonomous_system_organization","setter_type":null,"type":{".class":"UnionType","items":["builtins.str",{".class":"NoneType"}],"uses_pep604_syntax":false}}},"connection_type":{".class":"SymbolTableNode","kind":"Mdef","node":{".class":"Var","flags":["is_initialized_in_class","is_ready"],"fullname":"geoip2.records.Traits.connection_type","name":"connection_type","setter_type":null,"type":{".class":"UnionType","items":["builtins.str",{".class":"NoneType"}],"uses_pep604_syntax":false}}},"domain":{".class":"SymbolTableNode","kind":"Mdef","node":{".class":"Var","flags":["is_initialized_in_class","is_ready"],"fullname":"geoip2.records.Traits.domain","name":"domain","setter_type":null,"type":{".class":"UnionType","items":["builtins.str",{".class":"NoneType"}],"uses_pep604_syntax":false}}},"ip_address":{".class":"SymbolTableNode","kind":"Mdef","node":{".class":"Decorator","func":{".class":"FuncDef","abstract_status":0,"arg_kinds":[0],"arg_names":["self"],"dataclass_transform_spec":null,"deprecated":null,"flags":["is_property","is_decorated","is_trivial_self"],"fullname":"geoip2.records.Traits.ip_address","name":"ip_address","type":{".class":"CallableType","arg_kinds":[0],"arg_names":["self"],"arg_types":["geoip2.records.Traits"],"def_extras":{"first_arg":"self"},"fallback":"builtins.function","from_concatenate":false,"implicit":false,"imprecise_arg_kinds":false,"is_bound":false,"is_ellipsis_args":false,"name":"ip_address of Traits","ret_type":{".class":"UnionType","items":["ipaddress.IPv4Address","ipaddress.IPv6Address",{".class":"NoneType"}],"uses_pep604_syntax":false},"type_guard":null,"type_is":null,"unpack_kwargs":false,"variables":[]}},"is_overload":false,"var":{".class":"Var","flags":["is_initialized_in_class","is_property","is_ready","is_inferred"],"fullname":"geoip2.records.Traits.ip_address","name":"ip_address","setter_type":null,"type":{".class":"CallableType","arg_kinds":[0],"arg_names":["self"],"arg_types":["geoip2.records.Traits"],"def_extras":{"first_arg":"self"},"fallback":"builtins.function","from_concatenate":false,"implicit":false,"imprecise_arg_kinds":false,"is_bound":false,"is_ellipsis_args":false,"name":"ip_address of Traits","ret_type":{".class":"UnionType","items":["ipaddress.IPv4Address","ipaddress.IPv6Address",{".class":"NoneType"}],"uses_pep604_syntax":false},"type_guard":null,"type_is":null,"unpack_kwargs":false,"variables":[]}}}},"is_anonymous":{".class":"SymbolTableNode","kind":"Mdef","node":{".class":"Var","flags":["is_initialized_in_class","is_ready"],"fullname":"geoip2.records.Traits.is_anonymous","name":"is_anonymous","setter_type":null,"type":"builtins.bool"}},"is_anonymous_proxy":{".class":"SymbolTableNode","kind":"Mdef","node":{".class":"Var","flags":["is_initialized_in_class","is_ready"],"fullname":"geoip2.records.Traits.is_anonymous_proxy","name":"is_anonymous_proxy","setter_type":null,"type":"builtins.bool"}},"is_anonymous_vpn":{".class":"SymbolTableNode","kind":"Mdef","node":{".class":"Var","flags":["is_initialized_in_class","is_ready"],"fullname":"geoip2.records.Traits.is_anonymous_vpn","name":"is_anonymous_vpn","setter_type":null,"type":"builtins.bool"}},"is_anycast":{".class":"SymbolTableNode","kind":"Mdef","node":{".class":"Var","flags":["is_initialized_in_class","is_ready"],"fullname":"geoip2.records.Traits.is_anycast","name":"is_anycast","setter_type":null,"type":"builtins.bool"}},"is_hosting_provider":{".class":"SymbolTableNode","kind":"Mdef","node":{".class":"Var","flags":["is_initialized_in_class","is_ready"],"fullname":"geoip2.records.Traits.is_hosting_provider","name":"is_hosting_provider","setter_type":null,"type":"builtins.bool"}},"is_legitimate_proxy":{".class":"SymbolTableNode","kind":"Mdef","node":{".class":"Var","flags":["is_initialized_in_class","is_ready"],"fullname":"geoip2.records.Traits.is_legitimate_proxy","name":"is_legitimate_proxy","setter_type":null,"type":"builtins.bool"}},"is_public_proxy":{".class":"SymbolTableNode","kind":"Mdef","node":{".class":"Var","flags":["is_initialized_in_class","is_ready"],"fullname":"geoip2.records.Traits.is_public_proxy","name":"is_public_proxy","setter_type":null,"type":"builtins.bool"}},"is_residential_proxy":{".class":"SymbolTableNode","kind":"Mdef","node":{".class":"Var","flags":["is_initialized_in_class","is_ready"],"fullname":"geoip2.records.Traits.is_residential_proxy","name":"is_residential_proxy","setter_type":null,"type":"builtins.bool"}},"is_satellite_provider":{".class":"SymbolTableNode","kind":"Mdef","node":{".class":"Var","flags":["is_initialized_in_class","is_ready"],"fullname":"geoip2.records.Traits.is_satellite_provider","name":"is_satellite_provider","setter_type":null,"type":"builtins.bool"}},"is_tor_exit_node":{".class":"SymbolTableNode","kind":"Mdef","node":{".class":"Var","flags":["is_initialized_in_class","is_ready"],"fullname":"geoip2.records.Traits.is_tor_exit_node","name":"is_tor_exit_node","setter_type":null,"type":"builtins.bool"}},"isp":{".class":"SymbolTableNode","kind":"Mdef","node":{".class":"Var","flags":["is_initialized_in_class","is_ready"],"fullname":"geoip2.records.Traits.isp","name":"isp","setter_type":null,"type":{".class":"UnionType","items":["builtins.str",{".class":"NoneType"}],"uses_pep604_syntax":false}}},"mobile_country_code":{".class":"SymbolTableNode","kind":"Mdef","node":{".class":"Var","flags":["is_initialized_in_class","is_ready"],"fullname":"geoip2.records.Traits.mobile_country_code","name":"mobile_country_code","setter_type":null,"type":{".class":"UnionType","items":["builtins.str",{".class":"NoneType"}],"uses_pep604_syntax":false}}},"mobile_network_code":{".class":"SymbolTableNode","kind":"Mdef","node":{".class":"Var","flags":["is_initialized_in_class","is_ready"],"fullname":"geoip2.records.Traits.mobile_network_code","name":"mobile_network_code","setter_type":null,"type":{".class":"UnionType","items":["builtins.str",{".class":"NoneType"}],"uses_pep604_syntax":false}}},"network":{".class":"SymbolTableNode","kind":"Mdef","node":{".class":"Decorator","func":{".class":"FuncDef","abstract_status":0,"arg_kinds":[0],"arg_names":["self"],"dataclass_transform_spec":null,"deprecated":null,"flags":["is_property","is_decorated","is_trivial_self"],"fullname":"geoip2.records.Traits.network","name":"network","type":{".class":"CallableType","arg_kinds":[0],"arg_names":["self"],"arg_types":["geoip2.records.Traits"],"def_extras":{"first_arg":"self"},"fallback":"builtins.function","from_concatenate":false,"implicit":false,"imprecise_arg_kinds":false,"is_bound":false,"is_ellipsis_args":false,"name":"network of Traits","ret_type":{".class":"UnionType","items":["ipaddress.IPv4Network","ipaddress.IPv6Network",{".class":"NoneType"}],"uses_pep604_syntax":false},"type_guard":null,"type_is":null,"unpack_kwargs":false,"variables":[]}},"is_overload":false,"var":{".class":"Var","flags":["is_initialized_in_class","is_property","is_ready","is_inferred"],"fullname":"geoip2.records.Traits.network","name":"network","setter_type":null,"type":{".class":"CallableType","arg_kinds":[0],"arg_names":["self"],"arg_types":["geoip2.records.Traits"],"def_extras":{"first_arg":"self"},"fallback":"builtins.function","from_concatenate":false,"implicit":false,"imprecise_arg_kinds":false,"is_bound":false,"is_ellipsis_args":false,"name":"network of Traits","ret_type":{".class":"UnionType","items":["ipaddress.IPv4Network","ipaddress.IPv6Network",{".class":"NoneType"}],"uses_pep604_syntax":false},"type_guard":null,"type_is":null,"unpack_kwargs":false,"variables":[]}}}},"organization":{".class":"SymbolTableNode","kind":"Mdef","node":{".class":"Var","flags":["is_initialized_in_class","is_ready"],"fullname":"geoip2.records.Traits.organization","name":"organization","setter_type":null,"type":{".class":"UnionType","items":["builtins.str",{".class":"NoneType"}],"uses_pep604_syntax":false}}},"static_ip_score":{".class":"SymbolTableNode","kind":"Mdef","node":{".class":"Var","flags":["is_initialized_in_class","is_ready"],"fullname":"geoip2.records.Traits.static_ip_score","name":"static_ip_score","setter_type":null,"type":{".class":"UnionType","items":["builtins.float",{".class":"NoneType"}],"uses_pep604_syntax":false}}},"user_count":{".class":"SymbolTableNode","kind":"Mdef","node":{".class":"Var","flags":["is_initialized_in_class","is_ready"],"fullname":"geoip2.records.Traits.user_count","name":"user_count","setter_type":null,"type":{".class":"UnionType","items":["builtins.int",{".class":"NoneType"}],"uses_pep604_syntax":false}}},"user_type":{".class":"SymbolTableNode","kind":"Mdef","node":{".class":"Var","flags":["is_initialized_in_class","is_ready"],"fullname":"geoip2.records.Traits.user_type","name":"user_type","setter_type":null,"type":{".class":"UnionType","items":["builtins.str",{".class":"NoneType"}],"uses_pep604_syntax":false}}}},"self_type":{".class":"TypeVarType","default":{".class":"AnyType","missing_import_name":null,"source_any":null,"type_of_any":4},"fullname":"geoip2.records.Traits.Self","id":0,"name":"Self","namespace":"","upper_bound":"geoip2.records.Traits","values":[],"variance":0},"slots":null,"tuple_type":null,"type_vars":[],"typeddict_type":null}},"Union":{".class":"SymbolTableNode","cross_ref":"typing.Union","kind":"Gdef"},"__annotations__":{".class":"SymbolTableNode","kind":"Gdef","node":{".class":"Var","flags":["is_ready"],"fullname":"geoip2.records.__annotations__","name":"__annotations__","setter_type":null,"type":{".class":"Instance","args":["builtins.str",{".class":"AnyType","missing_import_name":null,"source_any":null,"type_of_any":6}],"extra_attrs":null,"type_ref":"builtins.dict"}}},"__doc__":{".class":"SymbolTableNode","kind":"Gdef","node":{".class":"Var","flags":["is_ready"],"fullname":"geoip2.records.__doc__","name":"__doc__","setter_type":null,"type":"builtins.str"}},"__file__":{".class":"SymbolTableNode","kind":"Gdef","node":{".class":"Var","flags":["is_ready"],"fullname":"geoip2.records.__file__","name":"__file__","setter_type":null,"type":"builtins.str"}},"__name__":{".class":"SymbolTableNode","kind":"Gdef","node":{".class":"Var","flags":["is_ready"],"fullname":"geoip2.records.__name__","name":"__name__","setter_type":null,"type":"builtins.str"}},"__package__":{".class":"SymbolTableNode","kind":"Gdef","node":{".class":"Var","flags":["is_ready"],"fullname":"geoip2.records.__package__","name":"__package__","setter_type":null,"type":"builtins.str"}},"__spec__":{".class":"SymbolTableNode","kind":"Gdef","node":{".class":"Var","flags":["is_ready"],"fullname":"geoip2.records.__spec__","name":"__spec__","setter_type":null,"type":"_frozen_importlib.ModuleSpec"}},"ipaddress":{".class":"SymbolTableNode","cross_ref":"ipaddress","kind":"Gdef"}},"path":"C:\\Users\\Komiya Yusuke\\AppData\\Local\\Programs\\Python\\Python313\\Lib\\site-packages\\geoip2\\records.py"}